{
  "CALL_VERSION":"1.0",
  "PROGRAM":"cpiprueba2.c",
  "NODE_NAME":"verode21",
  "SYSNAME":"Linux",
  "RELEASE":"5.4.0-0.bpo.2-amd64",
  "VERSION":"#1 SMP Debian 5.4.8-1~bpo10+1 (2020-01-07)",
  "PARALLEL_ID":"MPI",
  "cll_experiment":{
    "EXPERIMENT":"ker",
    "BEGIN_LINE":[
      28
    ],
    "END_LINE":[
      53
    ],
    "FORMULA":"p 0 ",
    "INFORMULA":"ker[0]",
    "MAXTESTS":131072,
    "DIMENSION":1,
    "NUMIDENTS":0,
    "IDENTS":[
    ],
    "OBSERVABLES":[
      "PAPI_L2_TCM",
      "PAPI_REAL_USEC"
    ],
    "COMPONENTS":[
      "1"
    ],
    "NUMTESTS":[
      40,
      40,
      40,
      40,
      40,
      40,
      40,
      40,
      40,
      40,
      40,
      40,
      40,
      40,
      40,
      40,
      40,
      40,
      40,
      40,
      40,
      40,
      40,
      40,
      40,
      40,
      40
    ],
    "machines":[
      "verode21",
      "verode21",
      "verode21",
      "verode21",
      "verode21",
      "verode21",
      "verode21",
      "verode21",
      "verode21",
      "verode21",
      "verode21",
      "verode21",
      "verode21",
      "verode21",
      "verode21",
      "verode21",
      "verode21",
      "verode21",
      "verode21",
      "verode21",
      "verode21",
      "verode21",
      "verode21",
      "verode21",
      "verode21",
      "verode21",
      "verode21"
    ],
    "headers":[
      "CPU",
      "NCPUS",
      "PAPI_REAL_USEC",
      "PAPI_L2_TCM"
    ],
    "sample":[
      [
        0,
        27,
        76868,
        1386
      ],
      [
        0,
        27,
        57686,
        242
      ],
      [
        0,
        27,
        57699,
        368
      ],
      [
        0,
        27,
        57964,
        222
      ],
      [
        0,
        27,
        57658,
        257
      ],
      [
        0,
        27,
        57676,
        230
      ],
      [
        0,
        27,
        57662,
        321
      ],
      [
        0,
        27,
        57770,
        193
      ],
      [
        0,
        27,
        57759,
        174
      ],
      [
        0,
        27,
        57682,
        278
      ],
      [
        0,
        27,
        57796,
        190
      ],
      [
        0,
        27,
        57671,
        279
      ],
      [
        0,
        27,
        57689,
        219
      ],
      [
        0,
        27,
        57660,
        191
      ],
      [
        0,
        27,
        57862,
        213
      ],
      [
        0,
        27,
        57962,
        576
      ],
      [
        0,
        27,
        57827,
        269
      ],
      [
        0,
        27,
        57893,
        144
      ],
      [
        0,
        27,
        57661,
        93
      ],
      [
        0,
        27,
        57684,
        59
      ],
      [
        0,
        27,
        57686,
        80
      ],
      [
        0,
        27,
        57768,
        69
      ],
      [
        0,
        27,
        57656,
        101
      ],
      [
        0,
        27,
        57642,
        56
      ],
      [
        0,
        27,
        57751,
        172
      ],
      [
        0,
        27,
        57667,
        119
      ],
      [
        0,
        27,
        57662,
        144
      ],
      [
        0,
        27,
        57664,
        300
      ],
      [
        0,
        27,
        57776,
        305
      ],
      [
        0,
        27,
        57644,
        65
      ],
      [
        0,
        27,
        57664,
        66
      ],
      [
        0,
        27,
        57768,
        73
      ],
      [
        0,
        27,
        57669,
        107
      ],
      [
        0,
        27,
        57807,
        67
      ],
      [
        0,
        27,
        57850,
        68
      ],
      [
        0,
        27,
        57761,
        45
      ],
      [
        0,
        27,
        57686,
        143
      ],
      [
        0,
        27,
        57662,
        43
      ],
      [
        0,
        27,
        57766,
        119
      ],
      [
        0,
        27,
        57665,
        39
      ],
      [
        1,
        27,
        68903,
        780
      ],
      [
        1,
        27,
        57553,
        102
      ],
      [
        1,
        27,
        57640,
        9
      ],
      [
        1,
        27,
        57771,
        8
      ],
      [
        1,
        27,
        57559,
        10
      ],
      [
        1,
        27,
        57556,
        17
      ],
      [
        1,
        27,
        57550,
        11
      ],
      [
        1,
        27,
        57661,
        12
      ],
      [
        1,
        27,
        57555,
        15
      ],
      [
        1,
        27,
        57567,
        5
      ],
      [
        1,
        27,
        57656,
        21
      ],
      [
        1,
        27,
        57555,
        9
      ],
      [
        1,
        27,
        57652,
        11
      ],
      [
        1,
        27,
        57550,
        5
      ],
      [
        1,
        27,
        57663,
        6
      ],
      [
        1,
        27,
        57746,
        205
      ],
      [
        1,
        27,
        57557,
        94
      ],
      [
        1,
        27,
        57754,
        11
      ],
      [
        1,
        27,
        57552,
        6
      ],
      [
        1,
        27,
        57560,
        8
      ],
      [
        1,
        27,
        57556,
        6
      ],
      [
        1,
        27,
        57657,
        17
      ],
      [
        1,
        27,
        57550,
        20
      ],
      [
        1,
        27,
        57547,
        6
      ],
      [
        1,
        27,
        57665,
        13
      ],
      [
        1,
        27,
        57550,
        2
      ],
      [
        1,
        27,
        57559,
        4
      ],
      [
        1,
        27,
        57547,
        8
      ],
      [
        1,
        27,
        57660,
        17
      ],
      [
        1,
        27,
        57545,
        7
      ],
      [
        1,
        27,
        57553,
        4
      ],
      [
        1,
        27,
        57658,
        6
      ],
      [
        1,
        27,
        57555,
        8
      ],
      [
        1,
        27,
        57550,
        3
      ],
      [
        1,
        27,
        57562,
        3
      ],
      [
        1,
        27,
        57655,
        1
      ],
      [
        1,
        27,
        57622,
        5
      ],
      [
        1,
        27,
        57559,
        7
      ],
      [
        1,
        27,
        57664,
        7
      ],
      [
        1,
        27,
        57549,
        7
      ],
      [
        2,
        27,
        68066,
        984
      ],
      [
        2,
        27,
        57654,
        80
      ],
      [
        2,
        27,
        57634,
        24
      ],
      [
        2,
        27,
        57954,
        31
      ],
      [
        2,
        27,
        57640,
        20
      ],
      [
        2,
        27,
        57634,
        13
      ],
      [
        2,
        27,
        57631,
        8
      ],
      [
        2,
        27,
        57738,
        19
      ],
      [
        2,
        27,
        57739,
        14
      ],
      [
        2,
        27,
        57633,
        15
      ],
      [
        2,
        27,
        57768,
        15
      ],
      [
        2,
        27,
        57627,
        8
      ],
      [
        2,
        27,
        57634,
        8
      ],
      [
        2,
        27,
        57625,
        8
      ],
      [
        2,
        27,
        57848,
        4
      ],
      [
        2,
        27,
        57917,
        138
      ],
      [
        2,
        27,
        57637,
        61
      ],
      [
        2,
        27,
        57792,
        23
      ],
      [
        2,
        27,
        57626,
        8
      ],
      [
        2,
        27,
        57673,
        7
      ],
      [
        2,
        27,
        57662,
        5
      ],
      [
        2,
        27,
        57739,
        13
      ],
      [
        2,
        27,
        57632,
        5
      ],
      [
        2,
        27,
        57625,
        4
      ],
      [
        2,
        27,
        57740,
        7
      ],
      [
        2,
        27,
        57658,
        19
      ],
      [
        2,
        27,
        57633,
        6
      ],
      [
        2,
        27,
        57633,
        5
      ],
      [
        2,
        27,
        57771,
        2
      ],
      [
        2,
        27,
        57633,
        2
      ],
      [
        2,
        27,
        57634,
        4
      ],
      [
        2,
        27,
        57737,
        2
      ],
      [
        2,
        27,
        57656,
        5
      ],
      [
        2,
        27,
        57629,
        7
      ],
      [
        2,
        27,
        57835,
        5
      ],
      [
        2,
        27,
        57737,
        5
      ],
      [
        2,
        27,
        57656,
        7
      ],
      [
        2,
        27,
        57636,
        1
      ],
      [
        2,
        27,
        57741,
        6
      ],
      [
        2,
        27,
        57630,
        6
      ],
      [
        3,
        27,
        67451,
        793
      ],
      [
        3,
        27,
        57564,
        91
      ],
      [
        3,
        27,
        57642,
        17
      ],
      [
        3,
        27,
        57768,
        20
      ],
      [
        3,
        27,
        57556,
        10
      ],
      [
        3,
        27,
        57551,
        12
      ],
      [
        3,
        27,
        57558,
        8
      ],
      [
        3,
        27,
        57654,
        17
      ],
      [
        3,
        27,
        57556,
        9
      ],
      [
        3,
        27,
        57553,
        13
      ],
      [
        3,
        27,
        57664,
        13
      ],
      [
        3,
        27,
        57553,
        8
      ],
      [
        3,
        27,
        57650,
        12
      ],
      [
        3,
        27,
        57559,
        8
      ],
      [
        3,
        27,
        57662,
        9
      ],
      [
        3,
        27,
        57759,
        204
      ],
      [
        3,
        27,
        57556,
        89
      ],
      [
        3,
        27,
        57755,
        16
      ],
      [
        3,
        27,
        57551,
        5
      ],
      [
        3,
        27,
        57559,
        12
      ],
      [
        3,
        27,
        57553,
        1
      ],
      [
        3,
        27,
        57662,
        30
      ],
      [
        3,
        27,
        57553,
        24
      ],
      [
        3,
        27,
        57546,
        10
      ],
      [
        3,
        27,
        57674,
        5
      ],
      [
        3,
        27,
        57555,
        4
      ],
      [
        3,
        27,
        57554,
        8
      ],
      [
        3,
        27,
        57551,
        7
      ],
      [
        3,
        27,
        57665,
        7
      ],
      [
        3,
        27,
        57551,
        5
      ],
      [
        3,
        27,
        57559,
        8
      ],
      [
        3,
        27,
        57652,
        5
      ],
      [
        3,
        27,
        57554,
        8
      ],
      [
        3,
        27,
        57549,
        8
      ],
      [
        3,
        27,
        57560,
        11
      ],
      [
        3,
        27,
        57653,
        2
      ],
      [
        3,
        27,
        57620,
        7
      ],
      [
        3,
        27,
        57548,
        8
      ],
      [
        3,
        27,
        57662,
        5
      ],
      [
        3,
        27,
        57553,
        3
      ],
      [
        4,
        27,
        69918,
        815
      ],
      [
        4,
        27,
        57666,
        87
      ],
      [
        4,
        27,
        57634,
        15
      ],
      [
        4,
        27,
        57958,
        7
      ],
      [
        4,
        27,
        57632,
        8
      ],
      [
        4,
        27,
        57642,
        10
      ],
      [
        4,
        27,
        57636,
        19
      ],
      [
        4,
        27,
        57739,
        13
      ],
      [
        4,
        27,
        57731,
        12
      ],
      [
        4,
        27,
        57638,
        31
      ],
      [
        4,
        27,
        57764,
        3
      ],
      [
        4,
        27,
        57630,
        13
      ],
      [
        4,
        27,
        57633,
        7
      ],
      [
        4,
        27,
        57630,
        10
      ],
      [
        4,
        27,
        57840,
        4
      ],
      [
        4,
        27,
        57920,
        172
      ],
      [
        4,
        27,
        57636,
        73
      ],
      [
        4,
        27,
        57793,
        15
      ],
      [
        4,
        27,
        57628,
        10
      ],
      [
        4,
        27,
        57678,
        7
      ],
      [
        4,
        27,
        57661,
        6
      ],
      [
        4,
        27,
        57739,
        11
      ],
      [
        4,
        27,
        57630,
        7
      ],
      [
        4,
        27,
        57636,
        8
      ],
      [
        4,
        27,
        57744,
        19
      ],
      [
        4,
        27,
        57637,
        6
      ],
      [
        4,
        27,
        57630,
        13
      ],
      [
        4,
        27,
        57637,
        6
      ],
      [
        4,
        27,
        57769,
        9
      ],
      [
        4,
        27,
        57633,
        6
      ],
      [
        4,
        27,
        57630,
        4
      ],
      [
        4,
        27,
        57738,
        7
      ],
      [
        4,
        27,
        57655,
        10
      ],
      [
        4,
        27,
        57635,
        2
      ],
      [
        4,
        27,
        57837,
        10
      ],
      [
        4,
        27,
        57739,
        2
      ],
      [
        4,
        27,
        57656,
        5
      ],
      [
        4,
        27,
        57638,
        8
      ],
      [
        4,
        27,
        57743,
        8
      ],
      [
        4,
        27,
        57630,
        8
      ],
      [
        5,
        27,
        68893,
        798
      ],
      [
        5,
        27,
        57556,
        105
      ],
      [
        5,
        27,
        57639,
        16
      ],
      [
        5,
        27,
        57773,
        9
      ],
      [
        5,
        27,
        57551,
        12
      ],
      [
        5,
        27,
        57554,
        11
      ],
      [
        5,
        27,
        57551,
        18
      ],
      [
        5,
        27,
        57664,
        12
      ],
      [
        5,
        27,
        57555,
        9
      ],
      [
        5,
        27,
        57549,
        15
      ],
      [
        5,
        27,
        57671,
        22
      ],
      [
        5,
        27,
        57554,
        6
      ],
      [
        5,
        27,
        57651,
        14
      ],
      [
        5,
        27,
        57550,
        6
      ],
      [
        5,
        27,
        57657,
        7
      ],
      [
        5,
        27,
        57558,
        33
      ],
      [
        5,
        27,
        57742,
        146
      ],
      [
        5,
        27,
        57762,
        45
      ],
      [
        5,
        27,
        57552,
        18
      ],
      [
        5,
        27,
        57553,
        19
      ],
      [
        5,
        27,
        57560,
        8
      ],
      [
        5,
        27,
        57659,
        13
      ],
      [
        5,
        27,
        57561,
        9
      ],
      [
        5,
        27,
        57547,
        7
      ],
      [
        5,
        27,
        57664,
        11
      ],
      [
        5,
        27,
        57553,
        15
      ],
      [
        5,
        27,
        57554,
        12
      ],
      [
        5,
        27,
        57554,
        5
      ],
      [
        5,
        27,
        57660,
        5
      ],
      [
        5,
        27,
        57549,
        8
      ],
      [
        5,
        27,
        57553,
        7
      ],
      [
        5,
        27,
        57660,
        2
      ],
      [
        5,
        27,
        57559,
        12
      ],
      [
        5,
        27,
        57549,
        4
      ],
      [
        5,
        27,
        57559,
        6
      ],
      [
        5,
        27,
        57648,
        7
      ],
      [
        5,
        27,
        57618,
        5
      ],
      [
        5,
        27,
        57559,
        6
      ],
      [
        5,
        27,
        57662,
        9
      ],
      [
        5,
        27,
        57559,
        7
      ],
      [
        6,
        27,
        62735,
        870
      ],
      [
        6,
        27,
        57664,
        149
      ],
      [
        6,
        27,
        57635,
        26
      ],
      [
        6,
        27,
        57947,
        27
      ],
      [
        6,
        27,
        57635,
        13
      ],
      [
        6,
        27,
        57630,
        8
      ],
      [
        6,
        27,
        57627,
        13
      ],
      [
        6,
        27,
        57740,
        19
      ],
      [
        6,
        27,
        57732,
        7
      ],
      [
        6,
        27,
        57636,
        26
      ],
      [
        6,
        27,
        57768,
        6
      ],
      [
        6,
        27,
        57642,
        11
      ],
      [
        6,
        27,
        57634,
        6
      ],
      [
        6,
        27,
        57629,
        6
      ],
      [
        6,
        27,
        57851,
        11
      ],
      [
        6,
        27,
        57920,
        181
      ],
      [
        6,
        27,
        57633,
        72
      ],
      [
        6,
        27,
        57793,
        17
      ],
      [
        6,
        27,
        57626,
        9
      ],
      [
        6,
        27,
        57675,
        5
      ],
      [
        6,
        27,
        57662,
        20
      ],
      [
        6,
        27,
        57742,
        20
      ],
      [
        6,
        27,
        57628,
        4
      ],
      [
        6,
        27,
        57630,
        3
      ],
      [
        6,
        27,
        57736,
        2
      ],
      [
        6,
        27,
        57628,
        5
      ],
      [
        6,
        27,
        57635,
        7
      ],
      [
        6,
        27,
        57635,
        3
      ],
      [
        6,
        27,
        57780,
        4
      ],
      [
        6,
        27,
        57637,
        3
      ],
      [
        6,
        27,
        57631,
        5
      ],
      [
        6,
        27,
        57734,
        6
      ],
      [
        6,
        27,
        57657,
        5
      ],
      [
        6,
        27,
        57629,
        4
      ],
      [
        6,
        27,
        57841,
        8
      ],
      [
        6,
        27,
        57740,
        2
      ],
      [
        6,
        27,
        57646,
        4
      ],
      [
        6,
        27,
        57638,
        3
      ],
      [
        6,
        27,
        57745,
        4
      ],
      [
        6,
        27,
        57633,
        5
      ],
      [
        7,
        27,
        67144,
        767
      ],
      [
        7,
        27,
        57566,
        112
      ],
      [
        7,
        27,
        57634,
        27
      ],
      [
        7,
        27,
        57763,
        18
      ],
      [
        7,
        27,
        57553,
        30
      ],
      [
        7,
        27,
        57558,
        12
      ],
      [
        7,
        27,
        57550,
        25
      ],
      [
        7,
        27,
        57655,
        13
      ],
      [
        7,
        27,
        57565,
        11
      ],
      [
        7,
        27,
        57553,
        10
      ],
      [
        7,
        27,
        57668,
        13
      ],
      [
        7,
        27,
        57554,
        14
      ],
      [
        7,
        27,
        57654,
        9
      ],
      [
        7,
        27,
        57556,
        6
      ],
      [
        7,
        27,
        57657,
        7
      ],
      [
        7,
        27,
        57554,
        46
      ],
      [
        7,
        27,
        57752,
        121
      ],
      [
        7,
        27,
        57764,
        69
      ],
      [
        7,
        27,
        57550,
        31
      ],
      [
        7,
        27,
        57554,
        4
      ],
      [
        7,
        27,
        57558,
        10
      ],
      [
        7,
        27,
        57662,
        18
      ],
      [
        7,
        27,
        57547,
        12
      ],
      [
        7,
        27,
        57561,
        8
      ],
      [
        7,
        27,
        57660,
        8
      ],
      [
        7,
        27,
        57574,
        23
      ],
      [
        7,
        27,
        57552,
        10
      ],
      [
        7,
        27,
        57557,
        8
      ],
      [
        7,
        27,
        57663,
        5
      ],
      [
        7,
        27,
        57548,
        11
      ],
      [
        7,
        27,
        57554,
        5
      ],
      [
        7,
        27,
        57661,
        7
      ],
      [
        7,
        27,
        57556,
        10
      ],
      [
        7,
        27,
        57549,
        11
      ],
      [
        7,
        27,
        57557,
        5
      ],
      [
        7,
        27,
        57652,
        6
      ],
      [
        7,
        27,
        57612,
        4
      ],
      [
        7,
        27,
        57552,
        8
      ],
      [
        7,
        27,
        57655,
        11
      ],
      [
        7,
        27,
        57556,
        5
      ],
      [
        8,
        27,
        69935,
        777
      ],
      [
        8,
        27,
        57663,
        69
      ],
      [
        8,
        27,
        57635,
        34
      ],
      [
        8,
        27,
        57952,
        31
      ],
      [
        8,
        27,
        57631,
        4
      ],
      [
        8,
        27,
        57629,
        14
      ],
      [
        8,
        27,
        57626,
        6
      ],
      [
        8,
        27,
        57744,
        7
      ],
      [
        8,
        27,
        57729,
        9
      ],
      [
        8,
        27,
        57629,
        10
      ],
      [
        8,
        27,
        57767,
        6
      ],
      [
        8,
        27,
        57641,
        12
      ],
      [
        8,
        27,
        57628,
        7
      ],
      [
        8,
        27,
        57631,
        4
      ],
      [
        8,
        27,
        57865,
        7
      ],
      [
        8,
        27,
        57717,
        46
      ],
      [
        8,
        27,
        57829,
        195
      ],
      [
        8,
        27,
        57813,
        31
      ],
      [
        8,
        27,
        57642,
        16
      ],
      [
        8,
        27,
        57677,
        13
      ],
      [
        8,
        27,
        57664,
        6
      ],
      [
        8,
        27,
        57740,
        28
      ],
      [
        8,
        27,
        57627,
        13
      ],
      [
        8,
        27,
        57628,
        2
      ],
      [
        8,
        27,
        57745,
        8
      ],
      [
        8,
        27,
        57635,
        4
      ],
      [
        8,
        27,
        57636,
        9
      ],
      [
        8,
        27,
        57634,
        3
      ],
      [
        8,
        27,
        57772,
        14
      ],
      [
        8,
        27,
        57632,
        4
      ],
      [
        8,
        27,
        57634,
        12
      ],
      [
        8,
        27,
        57748,
        4
      ],
      [
        8,
        27,
        57656,
        3
      ],
      [
        8,
        27,
        57628,
        10
      ],
      [
        8,
        27,
        57846,
        17
      ],
      [
        8,
        27,
        57740,
        5
      ],
      [
        8,
        27,
        57656,
        5
      ],
      [
        8,
        27,
        57636,
        5
      ],
      [
        8,
        27,
        57745,
        3
      ],
      [
        8,
        27,
        57631,
        3
      ],
      [
        9,
        27,
        62612,
        822
      ],
      [
        9,
        27,
        57561,
        113
      ],
      [
        9,
        27,
        57658,
        40
      ],
      [
        9,
        27,
        57779,
        17
      ],
      [
        9,
        27,
        57562,
        19
      ],
      [
        9,
        27,
        57563,
        14
      ],
      [
        9,
        27,
        57557,
        8
      ],
      [
        9,
        27,
        57665,
        10
      ],
      [
        9,
        27,
        57563,
        11
      ],
      [
        9,
        27,
        57567,
        10
      ],
      [
        9,
        27,
        57675,
        33
      ],
      [
        9,
        27,
        57565,
        8
      ],
      [
        9,
        27,
        57668,
        9
      ],
      [
        9,
        27,
        57563,
        3
      ],
      [
        9,
        27,
        57674,
        7
      ],
      [
        9,
        27,
        57570,
        39
      ],
      [
        9,
        27,
        57747,
        217
      ],
      [
        9,
        27,
        57771,
        52
      ],
      [
        9,
        27,
        57557,
        34
      ],
      [
        9,
        27,
        57565,
        9
      ],
      [
        9,
        27,
        57564,
        8
      ],
      [
        9,
        27,
        57685,
        34
      ],
      [
        9,
        27,
        57557,
        8
      ],
      [
        9,
        27,
        57561,
        5
      ],
      [
        9,
        27,
        57676,
        10
      ],
      [
        9,
        27,
        57561,
        7
      ],
      [
        9,
        27,
        57559,
        11
      ],
      [
        9,
        27,
        57567,
        4
      ],
      [
        9,
        27,
        57679,
        12
      ],
      [
        9,
        27,
        57558,
        9
      ],
      [
        9,
        27,
        57564,
        3
      ],
      [
        9,
        27,
        57668,
        7
      ],
      [
        9,
        27,
        57566,
        9
      ],
      [
        9,
        27,
        57556,
        13
      ],
      [
        9,
        27,
        57571,
        6
      ],
      [
        9,
        27,
        57660,
        9
      ],
      [
        9,
        27,
        57621,
        4
      ],
      [
        9,
        27,
        57560,
        4
      ],
      [
        9,
        27,
        57687,
        14
      ],
      [
        9,
        27,
        57561,
        8
      ],
      [
        10,
        27,
        68059,
        772
      ],
      [
        10,
        27,
        57664,
        58
      ],
      [
        10,
        27,
        57633,
        35
      ],
      [
        10,
        27,
        57948,
        19
      ],
      [
        10,
        27,
        57632,
        21
      ],
      [
        10,
        27,
        57632,
        8
      ],
      [
        10,
        27,
        57625,
        3
      ],
      [
        10,
        27,
        57736,
        18
      ],
      [
        10,
        27,
        57733,
        15
      ],
      [
        10,
        27,
        57664,
        16
      ],
      [
        10,
        27,
        57769,
        18
      ],
      [
        10,
        27,
        57628,
        9
      ],
      [
        10,
        27,
        57630,
        4
      ],
      [
        10,
        27,
        57627,
        6
      ],
      [
        10,
        27,
        57851,
        7
      ],
      [
        10,
        27,
        57713,
        25
      ],
      [
        10,
        27,
        57672,
        187
      ],
      [
        10,
        27,
        57788,
        16
      ],
      [
        10,
        27,
        57626,
        11
      ],
      [
        10,
        27,
        57673,
        4
      ],
      [
        10,
        27,
        57661,
        5
      ],
      [
        10,
        27,
        57739,
        7
      ],
      [
        10,
        27,
        57629,
        22
      ],
      [
        10,
        27,
        57630,
        4
      ],
      [
        10,
        27,
        57750,
        10
      ],
      [
        10,
        27,
        57632,
        5
      ],
      [
        10,
        27,
        57628,
        14
      ],
      [
        10,
        27,
        57664,
        3
      ],
      [
        10,
        27,
        57767,
        4
      ],
      [
        10,
        27,
        57637,
        2
      ],
      [
        10,
        27,
        57632,
        12
      ],
      [
        10,
        27,
        57733,
        8
      ],
      [
        10,
        27,
        57656,
        6
      ],
      [
        10,
        27,
        57630,
        2
      ],
      [
        10,
        27,
        57832,
        6
      ],
      [
        10,
        27,
        57742,
        3
      ],
      [
        10,
        27,
        57652,
        4
      ],
      [
        10,
        27,
        57633,
        2
      ],
      [
        10,
        27,
        57746,
        7
      ],
      [
        10,
        27,
        57638,
        5
      ],
      [
        11,
        27,
        68952,
        819
      ],
      [
        11,
        27,
        57558,
        89
      ],
      [
        11,
        27,
        57645,
        14
      ],
      [
        11,
        27,
        57778,
        20
      ],
      [
        11,
        27,
        57559,
        16
      ],
      [
        11,
        27,
        57554,
        6
      ],
      [
        11,
        27,
        57557,
        25
      ],
      [
        11,
        27,
        57672,
        104
      ],
      [
        11,
        27,
        57555,
        17
      ],
      [
        11,
        27,
        57556,
        9
      ],
      [
        11,
        27,
        57674,
        15
      ],
      [
        11,
        27,
        57553,
        2
      ],
      [
        11,
        27,
        57652,
        4
      ],
      [
        11,
        27,
        57553,
        6
      ],
      [
        11,
        27,
        57662,
        12
      ],
      [
        11,
        27,
        57555,
        12
      ],
      [
        11,
        27,
        57756,
        130
      ],
      [
        11,
        27,
        57760,
        61
      ],
      [
        11,
        27,
        57553,
        32
      ],
      [
        11,
        27,
        57560,
        23
      ],
      [
        11,
        27,
        57558,
        8
      ],
      [
        11,
        27,
        57664,
        19
      ],
      [
        11,
        27,
        57547,
        4
      ],
      [
        11,
        27,
        57552,
        6
      ],
      [
        11,
        27,
        57664,
        9
      ],
      [
        11,
        27,
        57557,
        7
      ],
      [
        11,
        27,
        57553,
        6
      ],
      [
        11,
        27,
        57548,
        5
      ],
      [
        11,
        27,
        57679,
        16
      ],
      [
        11,
        27,
        57552,
        3
      ],
      [
        11,
        27,
        57558,
        6
      ],
      [
        11,
        27,
        57656,
        14
      ],
      [
        11,
        27,
        57552,
        4
      ],
      [
        11,
        27,
        57551,
        4
      ],
      [
        11,
        27,
        57565,
        8
      ],
      [
        11,
        27,
        57653,
        2
      ],
      [
        11,
        27,
        57621,
        12
      ],
      [
        11,
        27,
        57554,
        12
      ],
      [
        11,
        27,
        57666,
        6
      ],
      [
        11,
        27,
        57555,
        5
      ],
      [
        12,
        27,
        67219,
        829
      ],
      [
        12,
        27,
        57678,
        77
      ],
      [
        12,
        27,
        57637,
        20
      ],
      [
        12,
        27,
        57956,
        14
      ],
      [
        12,
        27,
        57628,
        9
      ],
      [
        12,
        27,
        57638,
        32
      ],
      [
        12,
        27,
        57628,
        8
      ],
      [
        12,
        27,
        57739,
        3
      ],
      [
        12,
        27,
        57727,
        1
      ],
      [
        12,
        27,
        57638,
        24
      ],
      [
        12,
        27,
        57765,
        9
      ],
      [
        12,
        27,
        57632,
        7
      ],
      [
        12,
        27,
        57640,
        10
      ],
      [
        12,
        27,
        57624,
        5
      ],
      [
        12,
        27,
        57848,
        5
      ],
      [
        12,
        27,
        57720,
        40
      ],
      [
        12,
        27,
        57837,
        147
      ],
      [
        12,
        27,
        57791,
        40
      ],
      [
        12,
        27,
        57627,
        18
      ],
      [
        12,
        27,
        57671,
        9
      ],
      [
        12,
        27,
        57663,
        7
      ],
      [
        12,
        27,
        57733,
        28
      ],
      [
        12,
        27,
        57627,
        5
      ],
      [
        12,
        27,
        57628,
        20
      ],
      [
        12,
        27,
        57749,
        7
      ],
      [
        12,
        27,
        57639,
        3
      ],
      [
        12,
        27,
        57640,
        8
      ],
      [
        12,
        27,
        57631,
        2
      ],
      [
        12,
        27,
        57770,
        11
      ],
      [
        12,
        27,
        57635,
        4
      ],
      [
        12,
        27,
        57649,
        5
      ],
      [
        12,
        27,
        57732,
        3
      ],
      [
        12,
        27,
        57653,
        5
      ],
      [
        12,
        27,
        57629,
        7
      ],
      [
        12,
        27,
        57845,
        5
      ],
      [
        12,
        27,
        57741,
        4
      ],
      [
        12,
        27,
        57648,
        10
      ],
      [
        12,
        27,
        57632,
        6
      ],
      [
        12,
        27,
        57745,
        2
      ],
      [
        12,
        27,
        57632,
        8
      ],
      [
        13,
        27,
        67209,
        776
      ],
      [
        13,
        27,
        57557,
        64
      ],
      [
        13,
        27,
        57646,
        31
      ],
      [
        13,
        27,
        57776,
        11
      ],
      [
        13,
        27,
        57557,
        15
      ],
      [
        13,
        27,
        57553,
        26
      ],
      [
        13,
        27,
        57554,
        16
      ],
      [
        13,
        27,
        57656,
        8
      ],
      [
        13,
        27,
        57554,
        18
      ],
      [
        13,
        27,
        57569,
        15
      ],
      [
        13,
        27,
        57656,
        11
      ],
      [
        13,
        27,
        57553,
        11
      ],
      [
        13,
        27,
        57649,
        10
      ],
      [
        13,
        27,
        57550,
        5
      ],
      [
        13,
        27,
        57673,
        17
      ],
      [
        13,
        27,
        57572,
        52
      ],
      [
        13,
        27,
        57741,
        219
      ],
      [
        13,
        27,
        57761,
        76
      ],
      [
        13,
        27,
        57551,
        23
      ],
      [
        13,
        27,
        57560,
        7
      ],
      [
        13,
        27,
        57555,
        14
      ],
      [
        13,
        27,
        57664,
        10
      ],
      [
        13,
        27,
        57550,
        16
      ],
      [
        13,
        27,
        57548,
        11
      ],
      [
        13,
        27,
        57659,
        11
      ],
      [
        13,
        27,
        57558,
        24
      ],
      [
        13,
        27,
        57564,
        7
      ],
      [
        13,
        27,
        57550,
        15
      ],
      [
        13,
        27,
        57664,
        8
      ],
      [
        13,
        27,
        57551,
        6
      ],
      [
        13,
        27,
        57555,
        4
      ],
      [
        13,
        27,
        57655,
        5
      ],
      [
        13,
        27,
        57559,
        17
      ],
      [
        13,
        27,
        57551,
        3
      ],
      [
        13,
        27,
        57557,
        6
      ],
      [
        13,
        27,
        57656,
        3
      ],
      [
        13,
        27,
        57616,
        3
      ],
      [
        13,
        27,
        57559,
        7
      ],
      [
        13,
        27,
        57660,
        12
      ],
      [
        13,
        27,
        57555,
        4
      ],
      [
        14,
        27,
        66066,
        768
      ],
      [
        14,
        27,
        57669,
        119
      ],
      [
        14,
        27,
        57632,
        33
      ],
      [
        14,
        27,
        57958,
        15
      ],
      [
        14,
        27,
        57631,
        7
      ],
      [
        14,
        27,
        57636,
        10
      ],
      [
        14,
        27,
        57627,
        3
      ],
      [
        14,
        27,
        57741,
        14
      ],
      [
        14,
        27,
        57731,
        7
      ],
      [
        14,
        27,
        57631,
        11
      ],
      [
        14,
        27,
        57777,
        31
      ],
      [
        14,
        27,
        57630,
        7
      ],
      [
        14,
        27,
        57638,
        9
      ],
      [
        14,
        27,
        57627,
        5
      ],
      [
        14,
        27,
        57848,
        3
      ],
      [
        14,
        27,
        57722,
        44
      ],
      [
        14,
        27,
        57832,
        135
      ],
      [
        14,
        27,
        57793,
        26
      ],
      [
        14,
        27,
        57625,
        20
      ],
      [
        14,
        27,
        57673,
        10
      ],
      [
        14,
        27,
        57661,
        4
      ],
      [
        14,
        27,
        57735,
        5
      ],
      [
        14,
        27,
        57631,
        4
      ],
      [
        14,
        27,
        57627,
        11
      ],
      [
        14,
        27,
        57741,
        6
      ],
      [
        14,
        27,
        57634,
        2
      ],
      [
        14,
        27,
        57632,
        6
      ],
      [
        14,
        27,
        57646,
        13
      ],
      [
        14,
        27,
        57762,
        14
      ],
      [
        14,
        27,
        57633,
        2
      ],
      [
        14,
        27,
        57629,
        7
      ],
      [
        14,
        27,
        57733,
        5
      ],
      [
        14,
        27,
        57662,
        23
      ],
      [
        14,
        27,
        57628,
        12
      ],
      [
        14,
        27,
        57836,
        5
      ],
      [
        14,
        27,
        57737,
        10
      ],
      [
        14,
        27,
        57655,
        11
      ],
      [
        14,
        27,
        57632,
        9
      ],
      [
        14,
        27,
        57742,
        7
      ],
      [
        14,
        27,
        57634,
        1
      ],
      [
        15,
        27,
        68902,
        871
      ],
      [
        15,
        27,
        57566,
        69
      ],
      [
        15,
        27,
        57633,
        21
      ],
      [
        15,
        27,
        57773,
        21
      ],
      [
        15,
        27,
        57556,
        13
      ],
      [
        15,
        27,
        57552,
        7
      ],
      [
        15,
        27,
        57552,
        7
      ],
      [
        15,
        27,
        57655,
        12
      ],
      [
        15,
        27,
        57553,
        7
      ],
      [
        15,
        27,
        57552,
        5
      ],
      [
        15,
        27,
        57669,
        14
      ],
      [
        15,
        27,
        57552,
        10
      ],
      [
        15,
        27,
        57653,
        7
      ],
      [
        15,
        27,
        57557,
        7
      ],
      [
        15,
        27,
        57662,
        9
      ],
      [
        15,
        27,
        57561,
        40
      ],
      [
        15,
        27,
        57731,
        138
      ],
      [
        15,
        27,
        57763,
        64
      ],
      [
        15,
        27,
        57551,
        11
      ],
      [
        15,
        27,
        57559,
        13
      ],
      [
        15,
        27,
        57560,
        21
      ],
      [
        15,
        27,
        57656,
        8
      ],
      [
        15,
        27,
        57554,
        7
      ],
      [
        15,
        27,
        57547,
        3
      ],
      [
        15,
        27,
        57675,
        12
      ],
      [
        15,
        27,
        57556,
        8
      ],
      [
        15,
        27,
        57550,
        6
      ],
      [
        15,
        27,
        57550,
        3
      ],
      [
        15,
        27,
        57663,
        4
      ],
      [
        15,
        27,
        57549,
        13
      ],
      [
        15,
        27,
        57551,
        11
      ],
      [
        15,
        27,
        57654,
        3
      ],
      [
        15,
        27,
        57557,
        13
      ],
      [
        15,
        27,
        57553,
        13
      ],
      [
        15,
        27,
        57561,
        8
      ],
      [
        15,
        27,
        57654,
        8
      ],
      [
        15,
        27,
        57617,
        5
      ],
      [
        15,
        27,
        57549,
        9
      ],
      [
        15,
        27,
        57667,
        17
      ],
      [
        15,
        27,
        57555,
        7
      ],
      [
        16,
        27,
        65502,
        739
      ],
      [
        16,
        27,
        57661,
        109
      ],
      [
        16,
        27,
        57638,
        33
      ],
      [
        16,
        27,
        57954,
        28
      ],
      [
        16,
        27,
        57630,
        11
      ],
      [
        16,
        27,
        57634,
        5
      ],
      [
        16,
        27,
        57627,
        13
      ],
      [
        16,
        27,
        57738,
        16
      ],
      [
        16,
        27,
        57729,
        17
      ],
      [
        16,
        27,
        57627,
        6
      ],
      [
        16,
        27,
        57771,
        16
      ],
      [
        16,
        27,
        57627,
        4
      ],
      [
        16,
        27,
        57641,
        8
      ],
      [
        16,
        27,
        57628,
        4
      ],
      [
        16,
        27,
        57843,
        13
      ],
      [
        16,
        27,
        57712,
        48
      ],
      [
        16,
        27,
        57808,
        130
      ],
      [
        16,
        27,
        57793,
        53
      ],
      [
        16,
        27,
        57658,
        33
      ],
      [
        16,
        27,
        57679,
        7
      ],
      [
        16,
        27,
        57667,
        14
      ],
      [
        16,
        27,
        57748,
        51
      ],
      [
        16,
        27,
        57628,
        5
      ],
      [
        16,
        27,
        57622,
        5
      ],
      [
        16,
        27,
        57746,
        5
      ],
      [
        16,
        27,
        57640,
        4
      ],
      [
        16,
        27,
        57631,
        7
      ],
      [
        16,
        27,
        57632,
        6
      ],
      [
        16,
        27,
        57769,
        7
      ],
      [
        16,
        27,
        57638,
        2
      ],
      [
        16,
        27,
        57634,
        10
      ],
      [
        16,
        27,
        57739,
        8
      ],
      [
        16,
        27,
        57649,
        5
      ],
      [
        16,
        27,
        57628,
        10
      ],
      [
        16,
        27,
        57841,
        7
      ],
      [
        16,
        27,
        57738,
        4
      ],
      [
        16,
        27,
        57655,
        8
      ],
      [
        16,
        27,
        57635,
        3
      ],
      [
        16,
        27,
        57749,
        5
      ],
      [
        16,
        27,
        57633,
        4
      ],
      [
        17,
        27,
        67135,
        843
      ],
      [
        17,
        27,
        57562,
        126
      ],
      [
        17,
        27,
        57649,
        50
      ],
      [
        17,
        27,
        57775,
        15
      ],
      [
        17,
        27,
        57558,
        13
      ],
      [
        17,
        27,
        57555,
        5
      ],
      [
        17,
        27,
        57554,
        20
      ],
      [
        17,
        27,
        57656,
        13
      ],
      [
        17,
        27,
        57553,
        7
      ],
      [
        17,
        27,
        57558,
        7
      ],
      [
        17,
        27,
        57665,
        5
      ],
      [
        17,
        27,
        57559,
        6
      ],
      [
        17,
        27,
        57654,
        20
      ],
      [
        17,
        27,
        57551,
        6
      ],
      [
        17,
        27,
        57659,
        16
      ],
      [
        17,
        27,
        57565,
        29
      ],
      [
        17,
        27,
        57746,
        159
      ],
      [
        17,
        27,
        57761,
        74
      ],
      [
        17,
        27,
        57549,
        20
      ],
      [
        17,
        27,
        57557,
        12
      ],
      [
        17,
        27,
        57555,
        17
      ],
      [
        17,
        27,
        57663,
        32
      ],
      [
        17,
        27,
        57547,
        15
      ],
      [
        17,
        27,
        57545,
        14
      ],
      [
        17,
        27,
        57670,
        9
      ],
      [
        17,
        27,
        57555,
        10
      ],
      [
        17,
        27,
        57556,
        3
      ],
      [
        17,
        27,
        57550,
        12
      ],
      [
        17,
        27,
        57662,
        4
      ],
      [
        17,
        27,
        57548,
        5
      ],
      [
        17,
        27,
        57552,
        4
      ],
      [
        17,
        27,
        57657,
        3
      ],
      [
        17,
        27,
        57552,
        3
      ],
      [
        17,
        27,
        57549,
        6
      ],
      [
        17,
        27,
        57559,
        8
      ],
      [
        17,
        27,
        57656,
        7
      ],
      [
        17,
        27,
        57617,
        8
      ],
      [
        17,
        27,
        57552,
        3
      ],
      [
        17,
        27,
        57663,
        7
      ],
      [
        17,
        27,
        57552,
        5
      ],
      [
        18,
        27,
        68058,
        829
      ],
      [
        18,
        27,
        57670,
        108
      ],
      [
        18,
        27,
        57631,
        30
      ],
      [
        18,
        27,
        57960,
        16
      ],
      [
        18,
        27,
        57638,
        16
      ],
      [
        18,
        27,
        57646,
        11
      ],
      [
        18,
        27,
        57627,
        12
      ],
      [
        18,
        27,
        57743,
        11
      ],
      [
        18,
        27,
        57731,
        8
      ],
      [
        18,
        27,
        57632,
        10
      ],
      [
        18,
        27,
        57771,
        3
      ],
      [
        18,
        27,
        57628,
        10
      ],
      [
        18,
        27,
        57632,
        3
      ],
      [
        18,
        27,
        57631,
        8
      ],
      [
        18,
        27,
        57846,
        6
      ],
      [
        18,
        27,
        57718,
        40
      ],
      [
        18,
        27,
        57834,
        164
      ],
      [
        18,
        27,
        57785,
        67
      ],
      [
        18,
        27,
        57627,
        13
      ],
      [
        18,
        27,
        57675,
        13
      ],
      [
        18,
        27,
        57662,
        3
      ],
      [
        18,
        27,
        57741,
        13
      ],
      [
        18,
        27,
        57635,
        11
      ],
      [
        18,
        27,
        57629,
        4
      ],
      [
        18,
        27,
        57745,
        8
      ],
      [
        18,
        27,
        57634,
        5
      ],
      [
        18,
        27,
        57630,
        9
      ],
      [
        18,
        27,
        57629,
        4
      ],
      [
        18,
        27,
        57768,
        7
      ],
      [
        18,
        27,
        57635,
        3
      ],
      [
        18,
        27,
        57630,
        4
      ],
      [
        18,
        27,
        57735,
        5
      ],
      [
        18,
        27,
        57657,
        4
      ],
      [
        18,
        27,
        57636,
        6
      ],
      [
        18,
        27,
        57838,
        7
      ],
      [
        18,
        27,
        57741,
        7
      ],
      [
        18,
        27,
        57655,
        9
      ],
      [
        18,
        27,
        57632,
        11
      ],
      [
        18,
        27,
        57742,
        3
      ],
      [
        18,
        27,
        57650,
        8
      ],
      [
        19,
        27,
        68902,
        812
      ],
      [
        19,
        27,
        57561,
        124
      ],
      [
        19,
        27,
        57645,
        27
      ],
      [
        19,
        27,
        57774,
        26
      ],
      [
        19,
        27,
        57553,
        13
      ],
      [
        19,
        27,
        57552,
        11
      ],
      [
        19,
        27,
        57549,
        7
      ],
      [
        19,
        27,
        57672,
        104
      ],
      [
        19,
        27,
        57552,
        19
      ],
      [
        19,
        27,
        57556,
        5
      ],
      [
        19,
        27,
        57663,
        9
      ],
      [
        19,
        27,
        57552,
        16
      ],
      [
        19,
        27,
        57649,
        4
      ],
      [
        19,
        27,
        57552,
        3
      ],
      [
        19,
        27,
        57664,
        10
      ],
      [
        19,
        27,
        57555,
        23
      ],
      [
        19,
        27,
        57742,
        165
      ],
      [
        19,
        27,
        57757,
        86
      ],
      [
        19,
        27,
        57552,
        17
      ],
      [
        19,
        27,
        57564,
        10
      ],
      [
        19,
        27,
        57554,
        6
      ],
      [
        19,
        27,
        57662,
        13
      ],
      [
        19,
        27,
        57550,
        14
      ],
      [
        19,
        27,
        57558,
        8
      ],
      [
        19,
        27,
        57662,
        12
      ],
      [
        19,
        27,
        57558,
        16
      ],
      [
        19,
        27,
        57550,
        7
      ],
      [
        19,
        27,
        57557,
        12
      ],
      [
        19,
        27,
        57666,
        4
      ],
      [
        19,
        27,
        57550,
        10
      ],
      [
        19,
        27,
        57553,
        5
      ],
      [
        19,
        27,
        57660,
        5
      ],
      [
        19,
        27,
        57557,
        3
      ],
      [
        19,
        27,
        57550,
        5
      ],
      [
        19,
        27,
        57556,
        15
      ],
      [
        19,
        27,
        57654,
        4
      ],
      [
        19,
        27,
        57614,
        2
      ],
      [
        19,
        27,
        57559,
        8
      ],
      [
        19,
        27,
        57663,
        5
      ],
      [
        19,
        27,
        57553,
        6
      ],
      [
        20,
        27,
        58636,
        879
      ],
      [
        20,
        27,
        57664,
        115
      ],
      [
        20,
        27,
        57637,
        35
      ],
      [
        20,
        27,
        57963,
        12
      ],
      [
        20,
        27,
        57638,
        7
      ],
      [
        20,
        27,
        57635,
        21
      ],
      [
        20,
        27,
        57630,
        11
      ],
      [
        20,
        27,
        57745,
        6
      ],
      [
        20,
        27,
        57737,
        12
      ],
      [
        20,
        27,
        57631,
        9
      ],
      [
        20,
        27,
        57763,
        5
      ],
      [
        20,
        27,
        57635,
        12
      ],
      [
        20,
        27,
        57631,
        10
      ],
      [
        20,
        27,
        57627,
        3
      ],
      [
        20,
        27,
        57846,
        19
      ],
      [
        20,
        27,
        57724,
        36
      ],
      [
        20,
        27,
        57825,
        154
      ],
      [
        20,
        27,
        57795,
        42
      ],
      [
        20,
        27,
        57628,
        11
      ],
      [
        20,
        27,
        57676,
        26
      ],
      [
        20,
        27,
        57660,
        6
      ],
      [
        20,
        27,
        57753,
        18
      ],
      [
        20,
        27,
        57626,
        10
      ],
      [
        20,
        27,
        57626,
        5
      ],
      [
        20,
        27,
        57737,
        4
      ],
      [
        20,
        27,
        57635,
        5
      ],
      [
        20,
        27,
        57631,
        4
      ],
      [
        20,
        27,
        57633,
        2
      ],
      [
        20,
        27,
        57768,
        7
      ],
      [
        20,
        27,
        57631,
        1
      ],
      [
        20,
        27,
        57629,
        13
      ],
      [
        20,
        27,
        57731,
        4
      ],
      [
        20,
        27,
        57661,
        5
      ],
      [
        20,
        27,
        57630,
        2
      ],
      [
        20,
        27,
        57840,
        15
      ],
      [
        20,
        27,
        57736,
        17
      ],
      [
        20,
        27,
        57655,
        3
      ],
      [
        20,
        27,
        57630,
        4
      ],
      [
        20,
        27,
        57747,
        8
      ],
      [
        20,
        27,
        57637,
        2
      ],
      [
        21,
        27,
        68899,
        764
      ],
      [
        21,
        27,
        57559,
        107
      ],
      [
        21,
        27,
        57651,
        31
      ],
      [
        21,
        27,
        57887,
        129
      ],
      [
        21,
        27,
        57552,
        25
      ],
      [
        21,
        27,
        57559,
        9
      ],
      [
        21,
        27,
        57558,
        36
      ],
      [
        21,
        27,
        57656,
        37
      ],
      [
        21,
        27,
        57552,
        4
      ],
      [
        21,
        27,
        57561,
        5
      ],
      [
        21,
        27,
        57666,
        8
      ],
      [
        21,
        27,
        57570,
        21
      ],
      [
        21,
        27,
        57654,
        12
      ],
      [
        21,
        27,
        57553,
        9
      ],
      [
        21,
        27,
        57660,
        3
      ],
      [
        21,
        27,
        57557,
        33
      ],
      [
        21,
        27,
        57733,
        171
      ],
      [
        21,
        27,
        57754,
        37
      ],
      [
        21,
        27,
        57553,
        32
      ],
      [
        21,
        27,
        57560,
        6
      ],
      [
        21,
        27,
        57619,
        62
      ],
      [
        21,
        27,
        57663,
        31
      ],
      [
        21,
        27,
        57546,
        22
      ],
      [
        21,
        27,
        57550,
        9
      ],
      [
        21,
        27,
        57660,
        5
      ],
      [
        21,
        27,
        57556,
        1
      ],
      [
        21,
        27,
        57562,
        27
      ],
      [
        21,
        27,
        57552,
        7
      ],
      [
        21,
        27,
        57677,
        11
      ],
      [
        21,
        27,
        57549,
        3
      ],
      [
        21,
        27,
        57553,
        8
      ],
      [
        21,
        27,
        57654,
        7
      ],
      [
        21,
        27,
        57555,
        7
      ],
      [
        21,
        27,
        57550,
        17
      ],
      [
        21,
        27,
        57566,
        6
      ],
      [
        21,
        27,
        57655,
        7
      ],
      [
        21,
        27,
        57614,
        10
      ],
      [
        21,
        27,
        57610,
        28
      ],
      [
        21,
        27,
        57662,
        5
      ],
      [
        21,
        27,
        57553,
        2
      ],
      [
        22,
        27,
        76771,
        698
      ],
      [
        22,
        27,
        57668,
        97
      ],
      [
        22,
        27,
        57634,
        26
      ],
      [
        22,
        27,
        57955,
        16
      ],
      [
        22,
        27,
        57638,
        16
      ],
      [
        22,
        27,
        57639,
        18
      ],
      [
        22,
        27,
        57629,
        3
      ],
      [
        22,
        27,
        57743,
        13
      ],
      [
        22,
        27,
        57734,
        10
      ],
      [
        22,
        27,
        57631,
        15
      ],
      [
        22,
        27,
        57771,
        9
      ],
      [
        22,
        27,
        57631,
        6
      ],
      [
        22,
        27,
        57631,
        4
      ],
      [
        22,
        27,
        57632,
        4
      ],
      [
        22,
        27,
        57852,
        5
      ],
      [
        22,
        27,
        57723,
        61
      ],
      [
        22,
        27,
        57828,
        196
      ],
      [
        22,
        27,
        57794,
        46
      ],
      [
        22,
        27,
        57631,
        15
      ],
      [
        22,
        27,
        57676,
        8
      ],
      [
        22,
        27,
        57679,
        17
      ],
      [
        22,
        27,
        57742,
        24
      ],
      [
        22,
        27,
        57635,
        15
      ],
      [
        22,
        27,
        57634,
        10
      ],
      [
        22,
        27,
        57745,
        7
      ],
      [
        22,
        27,
        57636,
        5
      ],
      [
        22,
        27,
        57628,
        10
      ],
      [
        22,
        27,
        57634,
        15
      ],
      [
        22,
        27,
        57768,
        6
      ],
      [
        22,
        27,
        57637,
        9
      ],
      [
        22,
        27,
        57633,
        7
      ],
      [
        22,
        27,
        57736,
        7
      ],
      [
        22,
        27,
        57659,
        8
      ],
      [
        22,
        27,
        57632,
        3
      ],
      [
        22,
        27,
        57840,
        4
      ],
      [
        22,
        27,
        57741,
        5
      ],
      [
        22,
        27,
        57647,
        4
      ],
      [
        22,
        27,
        57634,
        6
      ],
      [
        22,
        27,
        57745,
        9
      ],
      [
        22,
        27,
        57648,
        4
      ],
      [
        23,
        27,
        66404,
        839
      ],
      [
        23,
        27,
        57557,
        83
      ],
      [
        23,
        27,
        57645,
        22
      ],
      [
        23,
        27,
        57780,
        12
      ],
      [
        23,
        27,
        57551,
        28
      ],
      [
        23,
        27,
        57555,
        11
      ],
      [
        23,
        27,
        57548,
        16
      ],
      [
        23,
        27,
        57667,
        87
      ],
      [
        23,
        27,
        57555,
        17
      ],
      [
        23,
        27,
        57553,
        13
      ],
      [
        23,
        27,
        57658,
        7
      ],
      [
        23,
        27,
        57555,
        10
      ],
      [
        23,
        27,
        57650,
        2
      ],
      [
        23,
        27,
        57550,
        4
      ],
      [
        23,
        27,
        57660,
        8
      ],
      [
        23,
        27,
        57557,
        9
      ],
      [
        23,
        27,
        57553,
        20
      ],
      [
        23,
        27,
        57756,
        9
      ],
      [
        23,
        27,
        57550,
        2
      ],
      [
        23,
        27,
        57555,
        5
      ],
      [
        23,
        27,
        57559,
        14
      ],
      [
        23,
        27,
        57655,
        8
      ],
      [
        23,
        27,
        57548,
        4
      ],
      [
        23,
        27,
        57560,
        15
      ],
      [
        23,
        27,
        57657,
        9
      ],
      [
        23,
        27,
        57554,
        3
      ],
      [
        23,
        27,
        57552,
        8
      ],
      [
        23,
        27,
        57550,
        4
      ],
      [
        23,
        27,
        57662,
        2
      ],
      [
        23,
        27,
        57545,
        12
      ],
      [
        23,
        27,
        57556,
        6
      ],
      [
        23,
        27,
        57659,
        11
      ],
      [
        23,
        27,
        57552,
        11
      ],
      [
        23,
        27,
        57709,
        81
      ],
      [
        23,
        27,
        57562,
        37
      ],
      [
        23,
        27,
        57649,
        9
      ],
      [
        23,
        27,
        57614,
        14
      ],
      [
        23,
        27,
        57551,
        20
      ],
      [
        23,
        27,
        57663,
        9
      ],
      [
        23,
        27,
        57547,
        7
      ],
      [
        24,
        27,
        66044,
        762
      ],
      [
        24,
        27,
        57659,
        85
      ],
      [
        24,
        27,
        57641,
        39
      ],
      [
        24,
        27,
        57952,
        18
      ],
      [
        24,
        27,
        57634,
        7
      ],
      [
        24,
        27,
        57634,
        4
      ],
      [
        24,
        27,
        57628,
        12
      ],
      [
        24,
        27,
        57740,
        18
      ],
      [
        24,
        27,
        57736,
        5
      ],
      [
        24,
        27,
        57630,
        9
      ],
      [
        24,
        27,
        57766,
        34
      ],
      [
        24,
        27,
        57633,
        11
      ],
      [
        24,
        27,
        57639,
        4
      ],
      [
        24,
        27,
        57628,
        5
      ],
      [
        24,
        27,
        57854,
        8
      ],
      [
        24,
        27,
        57724,
        32
      ],
      [
        24,
        27,
        57640,
        11
      ],
      [
        24,
        27,
        57790,
        5
      ],
      [
        24,
        27,
        57633,
        7
      ],
      [
        24,
        27,
        57676,
        1
      ],
      [
        24,
        27,
        57667,
        3
      ],
      [
        24,
        27,
        57736,
        4
      ],
      [
        24,
        27,
        57641,
        9
      ],
      [
        24,
        27,
        57630,
        6
      ],
      [
        24,
        27,
        57740,
        3
      ],
      [
        24,
        27,
        57635,
        3
      ],
      [
        24,
        27,
        57630,
        3
      ],
      [
        24,
        27,
        57636,
        5
      ],
      [
        24,
        27,
        57765,
        6
      ],
      [
        24,
        27,
        57635,
        3
      ],
      [
        24,
        27,
        57650,
        2
      ],
      [
        24,
        27,
        57742,
        4
      ],
      [
        24,
        27,
        57674,
        13
      ],
      [
        24,
        27,
        57806,
        90
      ],
      [
        24,
        27,
        57842,
        53
      ],
      [
        24,
        27,
        57736,
        7
      ],
      [
        24,
        27,
        57659,
        15
      ],
      [
        24,
        27,
        57638,
        6
      ],
      [
        24,
        27,
        57743,
        5
      ],
      [
        24,
        27,
        57629,
        2
      ],
      [
        25,
        27,
        68927,
        741
      ],
      [
        25,
        27,
        57555,
        67
      ],
      [
        25,
        27,
        57645,
        10
      ],
      [
        25,
        27,
        57779,
        20
      ],
      [
        25,
        27,
        57559,
        18
      ],
      [
        25,
        27,
        57556,
        15
      ],
      [
        25,
        27,
        57552,
        9
      ],
      [
        25,
        27,
        57670,
        97
      ],
      [
        25,
        27,
        57555,
        12
      ],
      [
        25,
        27,
        57559,
        5
      ],
      [
        25,
        27,
        57670,
        14
      ],
      [
        25,
        27,
        57558,
        3
      ],
      [
        25,
        27,
        57655,
        14
      ],
      [
        25,
        27,
        57554,
        3
      ],
      [
        25,
        27,
        57660,
        8
      ],
      [
        25,
        27,
        57552,
        21
      ],
      [
        25,
        27,
        57729,
        115
      ],
      [
        25,
        27,
        57753,
        39
      ],
      [
        25,
        27,
        57553,
        7
      ],
      [
        25,
        27,
        57560,
        10
      ],
      [
        25,
        27,
        57552,
        10
      ],
      [
        25,
        27,
        57660,
        17
      ],
      [
        25,
        27,
        57552,
        8
      ],
      [
        25,
        27,
        57547,
        12
      ],
      [
        25,
        27,
        57661,
        11
      ],
      [
        25,
        27,
        57557,
        9
      ],
      [
        25,
        27,
        57553,
        14
      ],
      [
        25,
        27,
        57564,
        7
      ],
      [
        25,
        27,
        57663,
        7
      ],
      [
        25,
        27,
        57549,
        14
      ],
      [
        25,
        27,
        57552,
        3
      ],
      [
        25,
        27,
        57658,
        4
      ],
      [
        25,
        27,
        57557,
        3
      ],
      [
        25,
        27,
        57555,
        6
      ],
      [
        25,
        27,
        57558,
        10
      ],
      [
        25,
        27,
        57655,
        9
      ],
      [
        25,
        27,
        57610,
        7
      ],
      [
        25,
        27,
        57561,
        7
      ],
      [
        25,
        27,
        57659,
        3
      ],
      [
        25,
        27,
        57551,
        10
      ],
      [
        26,
        27,
        69917,
        743
      ],
      [
        26,
        27,
        57663,
        59
      ],
      [
        26,
        27,
        57636,
        27
      ],
      [
        26,
        27,
        57953,
        11
      ],
      [
        26,
        27,
        57634,
        5
      ],
      [
        26,
        27,
        57635,
        8
      ],
      [
        26,
        27,
        57625,
        5
      ],
      [
        26,
        27,
        57751,
        69
      ],
      [
        26,
        27,
        57740,
        27
      ],
      [
        26,
        27,
        57640,
        12
      ],
      [
        26,
        27,
        57767,
        14
      ],
      [
        26,
        27,
        57631,
        8
      ],
      [
        26,
        27,
        57642,
        4
      ],
      [
        26,
        27,
        57635,
        3
      ],
      [
        26,
        27,
        57853,
        5
      ],
      [
        26,
        27,
        57694,
        8
      ],
      [
        26,
        27,
        57823,
        136
      ],
      [
        26,
        27,
        57792,
        46
      ],
      [
        26,
        27,
        57625,
        24
      ],
      [
        26,
        27,
        57675,
        3
      ],
      [
        26,
        27,
        57661,
        9
      ],
      [
        26,
        27,
        57741,
        20
      ],
      [
        26,
        27,
        57631,
        13
      ],
      [
        26,
        27,
        57628,
        4
      ],
      [
        26,
        27,
        57742,
        4
      ],
      [
        26,
        27,
        57630,
        3
      ],
      [
        26,
        27,
        57641,
        8
      ],
      [
        26,
        27,
        57633,
        7
      ],
      [
        26,
        27,
        57768,
        10
      ],
      [
        26,
        27,
        57634,
        4
      ],
      [
        26,
        27,
        57631,
        5
      ],
      [
        26,
        27,
        57737,
        2
      ],
      [
        26,
        27,
        57650,
        7
      ],
      [
        26,
        27,
        57630,
        3
      ],
      [
        26,
        27,
        57835,
        9
      ],
      [
        26,
        27,
        57738,
        6
      ],
      [
        26,
        27,
        57652,
        5
      ],
      [
        26,
        27,
        57637,
        6
      ],
      [
        26,
        27,
        57741,
        4
      ],
      [
        26,
        27,
        57633,
        5
      ]
    ]
  }
}